README.rst
setup.py
httpie_dag/__init__.py
httpie_dag/auth.py
httpie_dag/auth_v4.py
httpie_dag.egg-info/PKG-INFO
httpie_dag.egg-info/SOURCES.txt
httpie_dag.egg-info/dependency_links.txt
httpie_dag.egg-info/entry_points.txt
httpie_dag.egg-info/not-zip-safe
httpie_dag.egg-info/requires.txt
httpie_dag.egg-info/top_level.txt