Metadata-Version: 1.1
Name: httpie-dag
Version: 0.1.0
Summary: HTTPie plugin for IIJ GIO Storage & Analysis Service(DAG).
Home-page: https://github.com/iij/httpie-dag
Author: Internet Initiative Japan Inc.
Author-email: yosinobu@iij.ad.jp
License: MIT
Platform: UNKNOWN
Classifier: Development Status :: 5 - Production/Stable
Classifier: Programming Language :: Python
Classifier: Environment :: Plugins
Classifier: License :: OSI Approved :: BSD License
Classifier: Topic :: Internet :: WWW/HTTP
Classifier: Topic :: Utilities
